README.md
setup.py
aliyun_sms/__init__.py
aliyun_sms/core.py
aliyun_sms/signature.py
aliyun_sms/sms.py
aliyun_sms.egg-info/PKG-INFO
aliyun_sms.egg-info/SOURCES.txt
aliyun_sms.egg-info/dependency_links.txt
aliyun_sms.egg-info/requires.txt
aliyun_sms.egg-info/top_level.txt
aliyun_sms.egg-info/zip-safe
tests/__init__.py
tests/test_sign.py